pytest_kasima/__init__.py
pytest_kasima-0.1.5.dist-info/entry_points.txt
pytest_kasima-0.1.5.dist-info/METADATA
pytest_kasima-0.1.5.dist-info/WHEEL
pytest_kasima-0.1.5.dist-info/RECORD
