Metadata-Version: 2.1
Name: pytest-kasima
Version: 0.1.5
Summary: Display horizontal lines above and below the captured standard output for easy viewing.
Home-page: https://github.com/k4sima/pytest-kasima
License: MIT
Author: k4sima
Author-email: 44926913+k4sima@users.noreply.github.com
Requires-Python: >=3.10,<4.0
Classifier: Development Status :: 5 - Production/Stable
Classifier: Environment :: Console
Classifier: Intended Audience :: Developers
Classifier: Intended Audience :: Information Technology
Classifier: Intended Audience :: Science/Research
Classifier: Intended Audience :: System Administrators
Classifier: License :: OSI Approved :: MIT License
Classifier: Operating System :: MacOS
Classifier: Operating System :: Microsoft :: Windows
Classifier: Operating System :: POSIX :: Linux
Classifier: Programming Language :: Python :: 3
Classifier: Programming Language :: Python :: 3.10
Classifier: Programming Language :: Python :: 3.11
Provides-Extra: rich
Requires-Dist: pytest (>=7.2.1,<8.0.0)
Requires-Dist: rich ; extra == "rich"
Project-URL: Repository, https://github.com/k4sima/pytest-kasima
